ngl-0.0.1.data/purelib/ngl/__init__.py
ngl-0.0.1.data/purelib/ngl/_ngl.so
ngl-0.0.1.data/purelib/ngl/ngl.py
ngl-0.0.1.dist-info/LICENSE
ngl-0.0.1.dist-info/METADATA
ngl-0.0.1.dist-info/WHEEL
ngl-0.0.1.dist-info/top_level.txt
ngl-0.0.1.dist-info/RECORD
